bodhiq/__init__.py
bodhiq/cli.py
bodhiq/main.py
bodhiq/sci.py
bodhiq/utils.py
bodhiq/core/__init__.py
bodhiq/core/add.py
bodhiq/core/ls.py
bodhiq/core/q.py
bodhiq/core/reset.py
bodhiq/core/rm.py
bodhiq-0.1.1.dist-info/METADATA
bodhiq-0.1.1.dist-info/WHEEL
bodhiq-0.1.1.dist-info/entry_points.txt
bodhiq-0.1.1.dist-info/RECORD
