Metadata-Version: 2.4
Name: bodhiq
Version: 0.1.1
Summary: Personal memory search CLI inspired by Bodha
Author-email: Aman Shaw <amansahw4511@protonmail.com>
License: MIT
Keywords: cli,memory,personal-assistant,search,tfidf
Classifier: License :: OSI Approved :: MIT License
Classifier: Operating System :: OS Independent
Classifier: Programming Language :: Python :: 3
Classifier: Topic :: Utilities
Requires-Python: >=3.13
Requires-Dist: click>=8.3.1
Requires-Dist: meilisearch>=0.38.0
Requires-Dist: scikit-learn>=1.8.0
